Workbook

Sheet Company Profile
A1: AS Financial Services Pvt. Ltd.
A3: Company Profile
A4: Company Name | B4: AS Financial Services Pvt. Ltd.
A5: Project | B5: Complete Accounting Cycle
A6: Nature of Business | B6: Financial / Professional Services (simulated)
A7: Financial Year | B7: 1 April 2025 to 31 March 2026
A8: Currency | B8: Indian Rupees (INR)
A9: Project Type | B9: Simulated / Portfolio Project
A10: Purpose | B10: Demonstrate end-to-end accounting from transactions to financial statements.
A12: Accounting Cycle Flow
A13: Transactions → Journal Entries → Ledger → Trial Balance → Profit & Loss → Balance Sheet

Sheet Transactions
A1: Date | B1: Transaction ID | C1: Description | D1: Debit Account | E1: Credit Account | F1: Amount (INR) | G1: Remarks
A2: 45748 | B2: T001 | C2: Capital introduced by owner into bank | D2: Bank | E2: Capital | F2: 500000
A3: 45750 | B3: T002 | C3: Purchased office furniture by bank | D3: Furniture | E3: Bank | F3: 60000
A4: 45752 | B4: T003 | C4: Purchased computers/equipment by bank | D4: Computer Equipment | E4: Bank | F4: 80000
A5: 45754 | B5: T004 | C5: Paid office rent | D5: Rent Expense | E5: Bank | F5: 24000
A6: 45757 | B6: T005 | C6: Paid annual insurance premium | D6: Prepaid Insurance | E6: Bank | F6: 12000
A7: 45759 | B7: T006 | C7: Purchased office supplies by bank | D7: Office Supplies Expense | E7: Bank | F7: 5000
A8: 45762 | B8: T007 | C8: Received service revenue in bank | D8: Bank | E8: Service Revenue | F8: 100000
A9: 45767 | B9: T008 | C9: Provided services on credit to Client A | D9: Accounts Receivable - Client A | E9: Service Revenue | F9: 80000
A10: 45772 | B10: T009 | C10: Paid staff salaries | D10: Salary Expense | E10: Bank | F10: 30000
A11: 45782 | B11: T010 | C11: Paid electricity and utilities | D11: Utilities Expense | E11: Bank | F11: 6000
A12: 45787 | B12: T011 | C12: Paid advertising expense | D12: Advertising Expense | E12: Bank | F12: 8000
A13: 45795 | B13: T012 | C13: Received service revenue in bank | D13: Bank | E13: Service Revenue | F13: 120000
... A33: 45945 | B33: T032 | C33: Paid office rent | D33: Rent Expense | E33: Bank | F33: 24000
A34: 46112 | B34: T033 | C34: Recorded depreciation on office furniture | D34: Depreciation - Furniture | E34: Accumulated Depreciation - Furniture | F34: 6000 | G34: Year-end adjustment
A35: 46112 | B35: T034 | C35: Recorded depreciation on computer equipment | D35: Depreciation - Computer Equipment | E35: Accumulated Depreciation - Computer Equipment | F35: 16000 | G35: Year-end adjustment
A36: 46112 | B36: T035 | C36: Salary accrued but unpaid | D36: Salary Expense | E36: Salary Payable | F36: 5000 | G36: Year-end adjustment
A37: 46112 | B37: T036 | C37: Recognized insurance expense for the year | D37: Insurance Expense | E37: Prepaid Insurance | F37: 12000 | G37: Year-end adjustment

Sheet Journal Entries
A1: Date | B1: Transaction ID | C1: Particulars | D1: Debit (INR) | E1: Credit (INR)
A2: 45748 | B2: T001 | C2: Bank | D2: 500000 | E2: 0
A3: 45748 | B3: T001 | C3: To Capital | D3: 0 | E3: 500000
A4: 45750 | B4: T002 | C4: Furniture | D4: 60000 | E4: 0
A5: 45750 | B5: T002 | C5: To Bank | D5: 0 | E5: 60000
A6: 45752 | B6: T003 | C6: Computer Equipment | D6: 80000 | E6: 0
A7: 45752 | B7: T003 | C7: To Bank | D7: 0 | E7: 80000
A8: 45754 | B8: T004 | C8: Rent Expense | D8: 24000 | E8: 0
A9: 45754 | B9: T004 | C9: To Bank | D9: 0 | E9: 24000
A10: 45757 | B10: T005 | C10: Prepaid Insurance | D10: 12000 | E10: 0
A11: 45757 | B11: T005 | C11: To Bank | D11: 0 | E11: 12000
A12: 45759 | B12: T006 | C12: Office Supplies Expense | D12: 5000 | E12: 0
A13: 45759 | B13: T006 | C13: To Bank | D13: 0 | E13: 5000
... A73: 46112 | B73: T036 | C73: To Prepaid Insurance | D73: 0 | E73: 12000

Sheet Ledger
A1: Account | B1: Total Debit (INR) | C1: Total Credit (INR) | D1: Closing Balance (INR) | E1: Balance Type
A2: Bank | B2: =SUMIF('Journal Entries'!$C:$C,A2,'Journal Entries'!$D:$D) -> 1040000 | C2: =SUMIF('Journal Entries'!$C:$C," To "&A2,'Journal Entries'!$E:$E) -> 411000 | D2: =B2-C2 -> 629000 | E2: =IF(D2>0,"Debit",IF(D2<0,"Credit","Nil")) -> Debit
A3: Accounts Receivable - Client A | B3: =SUMIF('Journal Entries'!$C:$C,A3,'Journal Entries'!$D:$D) -> 80000 | C3: =SUMIF('Journal Entries'!$C:$C," To "&A3,'Journal Entries'!$E:$E) -> 80000 | D3: =B3-C3 -> 0 | E3: =IF(D3>0,"Debit",IF(D3<0,"Credit","Nil")) -> Nil
A4: Accounts Receivable - Client B | B4: =SUMIF('Journal Entries'!$C:$C,A4,'Journal Entries'!$D:$D) -> 70000 | C4: =SUMIF('Journal Entries'!$C:$C," To "&A4,'Journal Entries'!$E:$E) -> 40000 | D4: =B4-C4 -> 30000 | E4: =IF(D4>0,"Debit",IF(D4<0,"Credit","Nil")) -> Debit
A5: Accounts Receivable - Client C | B5: =SUMIF('Journal Entries'!$C:$C,A5,'Journal Entries'!$D:$D) -> 60000 | C5: =SUMIF('Journal Entries'!$C:$C," To "&A5,'Journal Entries'!$E:$E) -> 0 | D5: =B5-C5 -> 60000 | E5: =IF(D5>0,"Debit",IF(D5<0,"Credit","Nil")) -> Debit
A6: Furniture | B6: =SUMIF('Journal Entries'!$C:$C,A6,'Journal Entries'!$D:$D) -> 60000 | C6: =SUMIF('Journal Entries'!$C:$C," To "&A6,'Journal Entries'!$E:$E) -> 0 | D6: =B6-C6 -> 60000 | E6: =IF(D6>0,"Debit",IF(D6<0,"Credit","Nil")) -> Debit
A7: Computer Equipment | B7: =SUMIF('Journal Entries'!$C:$C,A7,'Journal Entries'!$D:$D) -> 80000 | C7: =SUMIF('Journal Entries'!$C:$C," To "&A7,'Journal Entries'!$E:$E) -> 0 | D7: =B7-C7 -> 80000 | E7: =IF(D7>0,"Debit",IF(D7<0,"Credit","Nil")) -> Debit
A8: Prepaid Insurance | B8: =SUMIF('Journal Entries'!$C:$C,A8,'Journal Entries'!$D:$D) -> 12000 | C8: =SUMIF('Journal Entries'!$C:$C," To "&A8,'Journal Entries'!$E:$E) -> 12000 | D8: =B8-C8 -> 0 | E8: =IF(D8>0,"Debit",IF(D8<0,"Credit","Nil")) -> Nil
A9: Office Supplies Expense | B9: =SUMIF('Journal Entries'!$C:$C,A9,'Journal Entries'!$D:$D) -> 9000 | C9: =SUMIF('Journal Entries'!$C:$C," To "&A9,'Journal Entries'!$E:$E) -> 0 | D9: =B9-C9 -> 9000 | E9: =IF(D9>0,"Debit",IF(D9<0,"Credit","Nil")) -> Debit
A10: Rent Expense | B10: =SUMIF('Journal Entries'!$C:$C,A10,'Journal Entries'!$D:$D) -> 96000 | C10: =SUMIF('Journal Entries'!$C:$C," To "&A10,'Journal Entries'!$E:$E) -> 0 | D10: =B10-C10 -> 96000 | E10: =IF(D10>0,"Debit",IF(D10<0,"Credit","Nil")) -> Debit
A11: Salary Expense | B11: =SUMIF('Journal Entries'!$C:$C,A11,'Journal Entries'!$D:$D) -> 125000 | C11: =SUMIF('Journal Entries'!$C:$C," To "&A11,'Journal Entries'!$E:$E) -> 0 | D11: =B11-C11 -> 125000 | E11: =IF(D11>0,"Debit",IF(D11<0,"Credit","Nil")) -> Debit
A12: Utilities Expense | B12: =SUMIF('Journal Entries'!$C:$C,A12,'Journal Entries'!$D:$D) -> 12500 | C12: =SUMIF('Journal Entries'!$C:$C," To "&A12,'Journal Entries'!$E:$E) -> 0 | D12: =B12-C12 -> 12500 | E12: =IF(D12>0,"Debit",IF(D12<0,"Credit","Nil")) -> Debit
A13: Advertising Expense | B13: =SUMIF('Journal Entries'!$C:$C,A13,'Journal Entries'!$D:$D) -> 13000 | C13: =SUMIF('Journal Entries'!$C:$C," To "&A13,'Journal Entries'!$E:$E) -> 0 | D13: =B13-C13 -> 13000 | E13: =IF(D13>0,"Debit",IF(D13<0,"Credit","Nil")) -> Debit
... A24: Capital | B24: =SUMIF('Journal Entries'!$C:$C,A24,'Journal Entries'!$D:$D) -> 0 | C24: =SUMIF('Journal Entries'!$C:$C," To "&A24,'Journal Entries'!$E:$E) -> 500000 | D24: =B24-C24 -> -500000 | E24: =IF(D24>0,"Debit",IF(D24<0,"Credit","Nil")) -> Credit

Sheet Trial Balance
A1: Account | B1: Debit (INR) | C1: Credit (INR)
A2: Bank | B2: =IF(Ledger!D2>0,Ledger!D2,0) -> 629000 | C2: =IF(Ledger!D2<0,-Ledger!D2,0) -> 0
A3: Accounts Receivable - Client A | B3: =IF(Ledger!D3>0,Ledger!D3,0) -> 0 | C3: =IF(Ledger!D3<0,-Ledger!D3,0) -> 0
A4: Accounts Receivable - Client B | B4: =IF(Ledger!D4>0,Ledger!D4,0) -> 30000 | C4: =IF(Ledger!D4<0,-Ledger!D4,0) -> 0
A5: Accounts Receivable - Client C | B5: =IF(Ledger!D5>0,Ledger!D5,0) -> 60000 | C5: =IF(Ledger!D5<0,-Ledger!D5,0) -> 0
A6: Furniture | B6: =IF(Ledger!D6>0,Ledger!D6,0) -> 60000 | C6: =IF(Ledger!D6<0,-Ledger!D6,0) -> 0
A7: Computer Equipment | B7: =IF(Ledger!D7>0,Ledger!D7,0) -> 80000 | C7: =IF(Ledger!D7<0,-Ledger!D7,0) -> 0
A8: Prepaid Insurance | B8: =IF(Ledger!D8>0,Ledger!D8,0) -> 0 | C8: =IF(Ledger!D8<0,-Ledger!D8,0) -> 0
A9: Office Supplies Expense | B9: =IF(Ledger!D9>0,Ledger!D9,0) -> 9000 | C9: =IF(Ledger!D9<0,-Ledger!D9,0) -> 0
A10: Rent Expense | B10: =IF(Ledger!D10>0,Ledger!D10,0) -> 96000 | C10: =IF(Ledger!D10<0,-Ledger!D10,0) -> 0
A11: Salary Expense | B11: =IF(Ledger!D11>0,Ledger!D11,0) -> 125000 | C11: =IF(Ledger!D11<0,-Ledger!D11,0) -> 0
A12: Utilities Expense | B12: =IF(Ledger!D12>0,Ledger!D12,0) -> 12500 | C12: =IF(Ledger!D12<0,-Ledger!D12,0) -> 0
A13: Advertising Expense | B13: =IF(Ledger!D13>0,Ledger!D13,0) -> 13000 | C13: =IF(Ledger!D13<0,-Ledger!D13,0) -> 0
... A24: Capital | B24: =IF(Ledger!D24>0,Ledger!D24,0) -> 0 | C24: =IF(Ledger!D24<0,-Ledger!D24,0) -> 500000
A25: TOTAL | B25: =SUM(B2:B24) -> 1157000 | C25: =SUM(C2:C24) -> 1157000
A27: Check (Debit - Credit) | B27: =B25-C25 -> 0

Sheet Profit & Loss
A1: AS Financial Services Pvt. Ltd.
A2: Profit & Loss Statement
A3: For the year ended 31 March 2026
A5: Income
A6: Service Revenue | B6: =SUMIF('Trial Balance'!A:A,A6,'Trial Balance'!C:C) -> 630000
A8: Expenses
A9: Office Supplies Expense | B9: =SUMIF('Trial Balance'!A:A,A9,'Trial Balance'!B:B) -> 9000
A10: Rent Expense | B10: =SUMIF('Trial Balance'!A:A,A10,'Trial Balance'!B:B) -> 96000
A11: Salary Expense | B11: =SUMIF('Trial Balance'!A:A,A11,'Trial Balance'!B:B) -> 125000
A12: Utilities Expense | B12: =SUMIF('Trial Balance'!A:A,A12,'Trial Balance'!B:B) -> 12500
A13: Advertising Expense | B13: =SUMIF('Trial Balance'!A:A,A13,'Trial Balance'!B:B) -> 13000
A14: Travel Expense | B14: =SUMIF('Trial Balance'!A:A,A14,'Trial Balance'!B:B) -> 7000
A15: Bank Charges Expense | B15: =SUMIF('Trial Balance'!A:A,A15,'Trial Balance'!B:B) -> 1500
A16: Insurance Expense | B16: =SUMIF('Trial Balance'!A:A,A16,'Trial Balance'!B:B) -> 12000
A17: Depreciation - Furniture | B17: =SUMIF('Trial Balance'!A:A,A17,'Trial Balance'!B:B) -> 6000
A18: Depreciation - Computer Equipment | B18: =SUMIF('Trial Balance'!A:A,A18,'Trial Balance'!B:B) -> 16000
A20: Total Expenses | B20: =SUM(B9:B18) -> 298000
A22: Net Profit | B22: =B6-B20 -> 332000

Sheet Balance Sheet
A1: AS Financial Services Pvt. Ltd.
A2: Balance Sheet
A3: As at 31 March 2026
A5: Assets
A6: Bank | B6: =SUMIF('Trial Balance'!A:A,A6,'Trial Balance'!B:B)-SUMIF('Trial Balance'!A:A,A6,'Trial Balance'!C:C) -> 629000
A7: Accounts Receivable - Client A | B7: =SUMIF('Trial Balance'!A:A,A7,'Trial Balance'!B:B)-SUMIF('Trial Balance'!A:A,A7,'Trial Balance'!C:C) -> 0
A8: Accounts Receivable - Client B | B8: =SUMIF('Trial Balance'!A:A,A8,'Trial Balance'!B:B)-SUMIF('Trial Balance'!A:A,A8,'Trial Balance'!C:C) -> 30000
A9: Accounts Receivable - Client C | B9: =SUMIF('Trial Balance'!A:A,A9,'Trial Balance'!B:B)-SUMIF('Trial Balance'!A:A,A9,'Trial Balance'!C:C) -> 60000
A10: Furniture | B10: =SUMIF('Trial Balance'!A:A,A10,'Trial Balance'!B:B)-SUMIF('Trial Balance'!A:A,A10,'Trial Balance'!C:C) -> 60000
A11: Computer Equipment | B11: =SUMIF('Trial Balance'!A:A,A11,'Trial Balance'!B:B)-SUMIF('Trial Balance'!A:A,A11,'Trial Balance'!C:C) -> 80000
A12: Prepaid Insurance | B12: =SUMIF('Trial Balance'!A:A,A12,'Trial Balance'!B:B)-SUMIF('Trial Balance'!A:A,A12,'Trial Balance'!C:C) -> 0
A13: Less: Accumulated Depreciation - Furniture | B13: =-SUMIF('Trial Balance'!A:A,"Accumulated Depreciation - Furniture",'Trial Balance'!C:C) -> -6000
A14: Less: Accumulated Depreciation - Computer Equipment | B14: =-SUMIF('Trial Balance'!A:A,"Accumulated Depreciation - Computer Equipment",'Trial Balance'!C:C) -> -16000
A16: Total Assets | B16: =SUM(B6:B12)+B13+B14 -> 837000
A18: Liabilities & Equity
A19: Accounts Payable - Vendor A | B19: =SUMIF('Trial Balance'!A:A,A19,'Trial Balance'!C:C)-SUMIF('Trial Balance'!A:A,A19,'Trial Balance'!B:B) -> 0
A20: Salary Payable | B20: =SUMIF('Trial Balance'!A:A,A20,'Trial Balance'!C:C)-SUMIF('Trial Balance'!A:A,A20,'Trial Balance'!B:B) -> 5000
A21: Capital | B21: =SUMIF('Trial Balance'!A:A,A21,'Trial Balance'!C:C)-SUMIF('Trial Balance'!A:A,A21,'Trial Balance'!B:B) -> 500000
A22: Current Year Net Profit | B22: ='Profit & Loss'!B22 -> 332000
A24: Total Liabilities & Equity | B24: =SUM(B19:B21)+B22 -> 837000
A26: Balance Check (Assets - L&E) | B26: =B16-B24 -> 0
